odoo/addons/product_supplierinfo_intercompany_multi_company/README.rst
odoo/addons/product_supplierinfo_intercompany_multi_company/__init__.py
odoo/addons/product_supplierinfo_intercompany_multi_company/__manifest__.py
odoo/addons/product_supplierinfo_intercompany_multi_company/i18n/product_supplierinfo_intercompany_multi_company.pot
odoo/addons/product_supplierinfo_intercompany_multi_company/models/__init__.py
odoo/addons/product_supplierinfo_intercompany_multi_company/models/product_intercompany_supplier_mixin.py
odoo/addons/product_supplierinfo_intercompany_multi_company/readme/CONTRIBUTORS.rst
odoo/addons/product_supplierinfo_intercompany_multi_company/readme/DESCRIPTION.rst
odoo/addons/product_supplierinfo_intercompany_multi_company/readme/USAGE.rst
odoo/addons/product_supplierinfo_intercompany_multi_company/static/description/icon.png
odoo/addons/product_supplierinfo_intercompany_multi_company/static/description/index.html
odoo14_addon_product_supplierinfo_intercompany_multi_company-14.0.1.1.0.dist-info/METADATA
odoo14_addon_product_supplierinfo_intercompany_multi_company-14.0.1.1.0.dist-info/WHEEL
odoo14_addon_product_supplierinfo_intercompany_multi_company-14.0.1.1.0.dist-info/top_level.txt
odoo14_addon_product_supplierinfo_intercompany_multi_company-14.0.1.1.0.dist-info/RECORD
