Metadata-Version: 2.1
Name: odoo14-addon-product-supplierinfo-intercompany-multi-company
Version: 14.0.1.1.0
Summary: Compatibility of product_multi_company and product_supplierinfo_intercompany
Home-page: https://github.com/OCA/multi-company
Author: Ilyas, Ooops404, Odoo Community Association (OCA)
Author-email: support@odoo-community.org
License: AGPL-3
Platform: UNKNOWN
Classifier: Programming Language :: Python
Classifier: Framework :: Odoo
Classifier: Framework :: Odoo :: 14.0
Classifier: License :: OSI Approved :: GNU Affero General Public License v3
Requires-Python: >=3.6
Requires-Dist: odoo14-addon-product-multi-company
Requires-Dist: odoo14-addon-product-supplierinfo-intercompany
Requires-Dist: odoo (<14.1dev,>=14.0a)
